poopip.py
poopip-0.2.2.dist-info/entry_points.txt
poopip-0.2.2.dist-info/LICENSE
poopip-0.2.2.dist-info/WHEEL
poopip-0.2.2.dist-info/METADATA
poopip-0.2.2.dist-info/RECORD
