Metadata-Version: 2.1
Name: poopip
Version: 0.2.2
Summary: poopip: for when pip is too slow 💩
Author-email: Oliver Margetts <oliver.margetts@gmail.com>
Classifier: License :: OSI Approved :: MIT License
Classifier: Topic :: Software Development :: Libraries :: Python Modules
Requires-Dist: tomli; python_version < '3.11'
Requires-Dist: mypy==1.7.1 ; extra == "test"
Requires-Dist: pytest==7.4.3 ; extra == "test"
Requires-Dist: ruff==0.1.8 ; extra == "test"
Project-URL: Home, https://github.com/olliemath/poop
Provides-Extra: test
